setup.cfg
setup.py
msrestore/__init__.py
msrestore.egg-info/PKG-INFO
msrestore.egg-info/SOURCES.txt
msrestore.egg-info/dependency_links.txt
msrestore.egg-info/entry_points.txt
msrestore.egg-info/not-zip-safe
msrestore.egg-info/top_level.txt