Metadata-Version: 1.0
Name: msrestore
Version: 0.1
Summary: Backup sync aid for mysql-zrm and more.
Home-page: http://github.com/cartlogic/msrestore
Author: Scott Torborg
Author-email: scott@cartlogic.com
License: MIT
Keywords: mysql backup restore copy
Platform: UNKNOWN
Classifier: License :: OSI Approved :: MIT License
Classifier: Programming Language :: Python :: 2.7
